pykkachu/__init__.py
pykkachu/actor.py
pykkachu/dispatcher.py
pykkachu/fleet.py
pykkachu/message.py
pykkachu-0.0.1.dist-info/LICENSE
pykkachu-0.0.1.dist-info/METADATA
pykkachu-0.0.1.dist-info/WHEEL
pykkachu-0.0.1.dist-info/top_level.txt
pykkachu-0.0.1.dist-info/RECORD
