Metadata-Version: 2.1
Name: pykkachu
Version: 0.0.1
Summary: An Actor Model which packages Pykka and FSMs
Home-page: https://github.com/amcknight/pykkachu
Author: Andrew McKnight
Author-email: thedonk@gmail.com
License: UNKNOWN
Platform: UNKNOWN
Classifier: Development Status :: 2 - Pre-Alpha
Classifier: Environment :: MacOS X
Classifier: Intended Audience :: Developers
Classifier: License :: OSI Approved :: GNU General Public License v3 (GPLv3)
Classifier: Natural Language :: English
Classifier: Operating System :: MacOS
Classifier: Programming Language :: Python :: 3
Requires-Python: >=3.6
